libs/__init__.py
libs/field_mappers/__init__.py
libs/field_mappers/dynamic_field_mappers.py
libs/field_mappers/static_mappers.py
libs/sftp/__init__.py
libs/sftp/client.py
workflow_helper_libs-0.1.3.dist-info/METADATA
workflow_helper_libs-0.1.3.dist-info/WHEEL
workflow_helper_libs-0.1.3.dist-info/RECORD
