Metadata-Version: 2.1
Name: workflow-helper-libs
Version: 0.1.3
Summary: Shared libraries used in cs-workflows
Author: CanonicalLtd
Author-email: jaas-dev@lists.launchpad.net
Requires-Python: >=3.8,<4.0
Classifier: Programming Language :: Python :: 3
Classifier: Programming Language :: Python :: 3.8
Classifier: Programming Language :: Python :: 3.9
Classifier: Programming Language :: Python :: 3.10
Classifier: Programming Language :: Python :: 3.11
Classifier: Programming Language :: Python :: 3.12
Requires-Dist: PGPy (>=0.6.0,<0.7.0)
Requires-Dist: paramiko (>=3.5.0,<4.0.0)
Project-URL: source, https://github.com/canonical/cs-workflows/tree/main/lib
